CNClassifier/__init__.py
CNClassifier/cnclassifier.py
CNClassifier/helper.py
CNClassifier-1.0.4.dist-info/METADATA
CNClassifier-1.0.4.dist-info/RECORD
CNClassifier-1.0.4.dist-info/WHEEL
CNClassifier-1.0.4.dist-info/top_level.txt
