Metadata-Version: 2.1
Name: CNClassifier
Version: 1.0.4
Summary: This package aims to do text classification of clinical notes.
Home-page: https://github.com/patrick013
Author: Wei Ruan
Author-email: acdmc.wruan@gmail.com
License: Apache License, Version 2.0
Platform: UNKNOWN
Classifier: Development Status :: 3 - Alpha
Classifier: Environment :: Web Environment
Classifier: Intended Audience :: Developers
Classifier: Operating System :: OS Independent
Classifier: Programming Language :: Python
